superstac/__init__.py
superstac/_logging.py
superstac/assets_mapper.py
superstac/catalog.py
superstac/catalog_registry.py
superstac/enums.py
superstac/exceptions.py
superstac/models.py
superstac/query.py
superstac/search.py
superstac/utils.py
superstac-0.1.0a2.dist-info/licenses/LICENSE
superstac-0.1.0a2.dist-info/METADATA
superstac-0.1.0a2.dist-info/WHEEL
superstac-0.1.0a2.dist-info/top_level.txt
superstac-0.1.0a2.dist-info/RECORD
