Metadata-Version: 2.4
Name: superstac
Version: 0.1.0a2
Summary: High-availability satellite imagery retrieval across multiple STAC catalogs.
Author-email: Emmanuel Jolaiya <emmanuel@spatialnode.net>
License: MIT
Classifier: Development Status :: 3 - Alpha
Classifier: Intended Audience :: Developers
Classifier: Intended Audience :: Science/Research
Classifier: Topic :: Scientific/Engineering :: GIS
Classifier: License :: OSI Approved :: MIT License
Classifier: Programming Language :: Python :: 3
Classifier: Programming Language :: Python :: 3.9
Classifier: Programming Language :: Python :: 3.10
Classifier: Programming Language :: Python :: 3.11
Classifier: Programming Language :: Python :: 3.12
Classifier: Operating System :: OS Independent
Requires-Python: >=3.9
License-File: LICENSE
Requires-Dist: pystac-client==0.8.5
Dynamic: license-file
